pypatchify/__init__.py
pypatchify/np.py
pypatchify/patch.py
pypatchify/pt.py
pypatchify-0.1.4.dist-info/LICENSE.md
pypatchify-0.1.4.dist-info/METADATA
pypatchify-0.1.4.dist-info/WHEEL
pypatchify-0.1.4.dist-info/top_level.txt
pypatchify-0.1.4.dist-info/RECORD
