Metadata-Version: 2.1
Name: pypatchify
Version: 0.1.4
Summary: Fast and easy image and n-dimensional volume patchification
Home-page: https://github.com/ndoll1998/patchify/tree/master
Author: Niclas Doll
Author-email: niclas@amazonis.net
Classifier: Environment :: GPU :: NVIDIA CUDA
Classifier: Intended Audience :: Science/Research
Classifier: License :: Freely Distributable
Classifier: License :: OSI Approved :: Apache Software License
Classifier: Programming Language :: Python :: 3
Classifier: Topic :: Scientific/Engineering :: Image Processing
License-File: LICENSE.md
